noci/__init__.py
noci/util.py
noci/.idea/.gitignore
noci/.idea/misc.xml
noci/.idea/modules.xml
noci/.idea/noci_ugyys.iml
noci/.idea/workspace.xml
noci/.idea/inspectionProfiles/Project_Default.xml
noci/.idea/inspectionProfiles/profiles_settings.xml
noci-0.0.5.dist-info/METADATA
noci-0.0.5.dist-info/WHEEL
noci-0.0.5.dist-info/licenses/LICENSE
noci-0.0.5.dist-info/RECORD
