Metadata-Version: 2.1
Name: noci
Version: 0.0.5
Summary: noci is a utility package for automation tasks
Author-email: ugyys <unigauldoth@gmail.com>
License: MIT License
License-File: LICENSE
Classifier: License :: OSI Approved :: MIT License
Classifier: Operating System :: OS Independent
Classifier: Programming Language :: Python :: 2.7
Classifier: Programming Language :: Python :: 3
Requires-Python: >=2.7
